mtg_scryfall_api/__init__.py
mtg_scryfall_api/mtg_scryfall_api.py
mtg_scryfall_api-0.1.0.dist-info/METADATA
mtg_scryfall_api-0.1.0.dist-info/WHEEL
mtg_scryfall_api-0.1.0.dist-info/licenses/LICENSE
mtg_scryfall_api-0.1.0.dist-info/RECORD
